balcony/__init__.py
balcony/botocore_utils.py
balcony/cli.py
balcony/custom_nodes/ec2.py
balcony/factories.py
balcony/logs.py
balcony/main.py
balcony/nodes.py
balcony/reader.py
balcony/registries.py
balcony/relations.py
balcony/rrr.py
balcony/utils.py
arzuhal-0.0.21.dist-info/entry_points.txt
arzuhal-0.0.21.dist-info/LICENSE
arzuhal-0.0.21.dist-info/WHEEL
arzuhal-0.0.21.dist-info/METADATA
arzuhal-0.0.21.dist-info/RECORD
